[
  {
    "category": "ポケモン",
    "card_id": "47142",
    "name": "ドラパルトex",
    "count": 3
  },
  {
    "category": "ポケモン",
    "card_id": "49972",
    "name": "ドロンチ",
    "count": 4
  },
  {
    "category": "ポケモン",
    "card_id": "49971",
    "name": "ドラメシヤ",
    "count": 4
  },
  {
    "category": "ポケモン",
    "card_id": "46047",
    "name": "ヨノワール",
    "count": 1
  },
  {
    "category": "ポケモン",
    "card_id": "46046",
    "name": "サマヨール",
    "count": 1
  },
  {
    "category": "ポケモン",
    "card_id": "46045",
    "name": "ヨマワル",
    "count": 2
  },
  {
    "category": "ポケモン",
    "card_id": "50067",
    "name": "ニャースex",
    "count": 2
  },
  {
    "category": "ポケモン",
    "card_id": "50004",
    "name": "キチキギスex",
    "count": 1
  },
  {
    "category": "ポケモン",
    "card_id": "49956",
    "name": "スボミー",
    "count": 1
  },
  {
    "category": "ポケモン",
    "card_id": "45849",
    "name": "マシマシラ",
    "count": 1
  },
  {
    "category": "ポケモン",
    "card_id": "47367",
    "name": "シェイミ",
    "count": 1
  },
  {
    "category": "ポケモン",
    "card_id": "48354",
    "name": "ファイヤー",
    "count": 1
  },
  {
    "category": "グッズ",
    "card_id": "48440",
    "name": "夜のタンカ",
    "count": 2
  },
  {
    "category": "グッズ",
    "card_id": "48467",
    "name": "なかよしポフィン",
    "count": 4
  },
  {
    "category": "グッズ",
    "card_id": "48468",
    "name": "ふしぎなアメ",
    "count": 2
  },
  {
    "category": "グッズ",
    "card_id": "49349",
    "name": "アンフェアスタンプ(ACE SPEC)",
    "count": 1
  },
  {
    "category": "グッズ",
    "card_id": "49976",
    "name": "ハイパーボール",
    "count": 4
  },
  {
    "category": "グッズ",
    "card_id": "50070",
    "name": "ポケパッド",
    "count": 4
  },
  {
    "category": "サポート",
    "card_id": "43300",
    "name": "ボスの指令",
    "count": 2
  },
  {
    "category": "サポート",
    "card_id": "46171",
    "name": "アカマツ",
    "count": 2
  },
  {
    "category": "サポート",
    "card_id": "46174",
    "name": "ブライア",
    "count": 1
  },
  {
    "category": "サポート",
    "card_id": "48443",
    "name": "リーリエの決心",
    "count": 4
  },
  {
    "category": "サポート",
    "card_id": "50074",
    "name": "メイのはげまし",
    "count": 1
  },
  {
    "category": "スタジアム",
    "card_id": "47536",
    "name": "ジャミングタワー",
    "count": 1
  },
  {
    "category": "スタジアム",
    "card_id": "48711",
    "name": "ロケット団の監視塔",
    "count": 2
  },
  {
    "category": "エネルギー",
    "card_id": "42948",
    "name": "基本超エネルギー",
    "count": 3
  },
  {
    "category": "エネルギー",
    "card_id": "42945",
    "name": "基本炎エネルギー",
    "count": 4
  },
  {
    "category": "エネルギー",
    "card_id": "42950",
    "name": "基本悪エネルギー",
    "count": 1
  }
]