[
  {
    "category": "ポケモン",
    "card_id": "48634",
    "name": "Nのゾロアークex",
    "count": 4
  },
  {
    "category": "ポケモン",
    "card_id": "49185",
    "name": "Nのゾロア",
    "count": 4
  },
  {
    "category": "ポケモン",
    "card_id": "49261",
    "name": "Nのレシラム",
    "count": 1
  },
  {
    "category": "ポケモン",
    "card_id": "49970",
    "name": "Nのゼクロム",
    "count": 1
  },
  {
    "category": "ポケモン",
    "card_id": "48651",
    "name": "Nのゼクロム",
    "count": 1
  },
  {
    "category": "ポケモン",
    "card_id": "48834",
    "name": "Nのダルマッカ",
    "count": 2
  },
  {
    "category": "ポケモン",
    "card_id": "48835",
    "name": "Nのヒヒダルマ",
    "count": 2
  },
  {
    "category": "ポケモン",
    "card_id": "49207",
    "name": "モモワロウex",
    "count": 1
  },
  {
    "category": "ポケモン",
    "card_id": "48249",
    "name": "マシマシラ",
    "count": 1
  },
  {
    "category": "ポケモン",
    "card_id": "48657",
    "name": "シャリタツ",
    "count": 1
  },
  {
    "category": "ポケモン",
    "card_id": "48636",
    "name": "キチキギスex",
    "count": 1
  },
  {
    "category": "グッズ",
    "card_id": "48668",
    "name": "Nのポイントアップ",
    "count": 3
  },
  {
    "category": "グッズ",
    "card_id": "49703",
    "name": "ポケパッド",
    "count": 3
  },
  {
    "category": "グッズ",
    "card_id": "49364",
    "name": "なかよしポフィン",
    "count": 4
  },
  {
    "category": "グッズ",
    "card_id": "49349",
    "name": "アンフェアスタンプ(ACE SPEC)",
    "count": 1
  },
  {
    "category": "グッズ",
    "card_id": "49600",
    "name": "ハイパーボール",
    "count": 2
  },
  {
    "category": "グッズ",
    "card_id": "48681",
    "name": "夜のタンカ",
    "count": 2
  },
  {
    "category": "グッズ",
    "card_id": "50156",
    "name": "スペシャルレッドカード",
    "count": 1
  },
  {
    "category": "ポケモンのどうぐ",
    "card_id": "49397",
    "name": "くさりもち",
    "count": 2
  },
  {
    "category": "サポート",
    "card_id": "49609",
    "name": "リーリエの決心",
    "count": 4
  },
  {
    "category": "サポート",
    "card_id": "49414",
    "name": "暗号マニアの解読",
    "count": 1
  },
  {
    "category": "サポート",
    "card_id": "49440",
    "name": "ボスの指令",
    "count": 3
  },
  {
    "category": "サポート",
    "card_id": "46604",
    "name": "からておうの稽古",
    "count": 1
  },
  {
    "category": "サポート",
    "card_id": "49415",
    "name": "アンズの秘技",
    "count": 1
  },
  {
    "category": "サポート",
    "card_id": "46442",
    "name": "シアノ",
    "count": 2
  },
  {
    "category": "サポート",
    "card_id": "49443",
    "name": "マツバの確信",
    "count": 1
  },
  {
    "category": "スタジアム",
    "card_id": "48703",
    "name": "Nの城",
    "count": 2
  },
  {
    "category": "エネルギー",
    "card_id": "48284",
    "name": "基本悪エネルギー",
    "count": 8
  }
]