[
  {
    "category": "ポケモン",
    "card_id": "45770",
    "name": "ドラメシヤ",
    "count": 4
  },
  {
    "category": "ポケモン",
    "card_id": "45771",
    "name": "ドロンチ",
    "count": 4
  },
  {
    "category": "ポケモン",
    "card_id": "45862",
    "name": "ドラパルトex",
    "count": 3
  },
  {
    "category": "ポケモン",
    "card_id": "47086",
    "name": "ノコッチ",
    "count": 2
  },
  {
    "category": "ポケモン",
    "card_id": "45203",
    "name": "ノココッチ",
    "count": 1
  },
  {
    "category": "ポケモン",
    "card_id": "47240",
    "name": "ノココッチex",
    "count": 1
  },
  {
    "category": "ポケモン",
    "card_id": "45849",
    "name": "マシマシラ",
    "count": 2
  },
  {
    "category": "ポケモン",
    "card_id": "49956",
    "name": "スボミー",
    "count": 1
  },
  {
    "category": "ポケモン",
    "card_id": "47367",
    "name": "シェイミ",
    "count": 1
  },
  {
    "category": "ポケモン",
    "card_id": "50067",
    "name": "ニャースex",
    "count": 1
  },
  {
    "category": "ポケモン",
    "card_id": "46058",
    "name": "キチキギスex",
    "count": 1
  },
  {
    "category": "グッズ",
    "card_id": "48467",
    "name": "なかよしポフィン",
    "count": 4
  },
  {
    "category": "グッズ",
    "card_id": "50070",
    "name": "ポケパッド",
    "count": 4
  },
  {
    "category": "グッズ",
    "card_id": "49976",
    "name": "ハイパーボール",
    "count": 4
  },
  {
    "category": "グッズ",
    "card_id": "48440",
    "name": "夜のタンカ",
    "count": 2
  },
  {
    "category": "グッズ",
    "card_id": "50156",
    "name": "スペシャルレッドカード",
    "count": 2
  },
  {
    "category": "ポケモンのどうぐ",
    "card_id": "45281",
    "name": "ヒーローマント(ACE SPEC)",
    "count": 1
  },
  {
    "category": "サポート",
    "card_id": "48443",
    "name": "リーリエの決心",
    "count": 4
  },
  {
    "category": "サポート",
    "card_id": "46171",
    "name": "アカマツ",
    "count": 3
  },
  {
    "category": "サポート",
    "card_id": "38062",
    "name": "ボスの指令",
    "count": 3
  },
  {
    "category": "サポート",
    "card_id": "48512",
    "name": "ヒカリ",
    "count": 1
  },
  {
    "category": "スタジアム",
    "card_id": "47796",
    "name": "危ない廃墟",
    "count": 2
  },
  {
    "category": "エネルギー",
    "card_id": "36467",
    "name": "基本超エネルギー",
    "count": 3
  },
  {
    "category": "エネルギー",
    "card_id": "49460",
    "name": "基本炎エネルギー",
    "count": 3
  },
  {
    "category": "エネルギー",
    "card_id": "49465",
    "name": "基本悪エネルギー",
    "count": 3
  }
]