[
  {
    "category": "ポケモン",
    "card_id": "48778",
    "name": "カジッチュ",
    "count": 4
  },
  {
    "category": "ポケモン",
    "card_id": "45703",
    "name": "カミッチュ",
    "count": 4
  },
  {
    "category": "ポケモン",
    "card_id": "45699",
    "name": "サルノリ",
    "count": 4
  },
  {
    "category": "ポケモン",
    "card_id": "45700",
    "name": "バチンキー",
    "count": 4
  },
  {
    "category": "ポケモン",
    "card_id": "45701",
    "name": "ゴリランダー",
    "count": 1
  },
  {
    "category": "ポケモン",
    "card_id": "45717",
    "name": "トサキント",
    "count": 1
  },
  {
    "category": "ポケモン",
    "card_id": "49862",
    "name": "コダック",
    "count": 1
  },
  {
    "category": "ポケモン",
    "card_id": "45231",
    "name": "シガロコ",
    "count": 1
  },
  {
    "category": "ポケモン",
    "card_id": "45232",
    "name": "ベラカス",
    "count": 1
  },
  {
    "category": "グッズ",
    "card_id": "45785",
    "name": "むしとりセット",
    "count": 4
  },
  {
    "category": "グッズ",
    "card_id": "45403",
    "name": "なかよしポフィン",
    "count": 4
  },
  {
    "category": "グッズ",
    "card_id": "49601",
    "name": "ポケパッド",
    "count": 4
  },
  {
    "category": "グッズ",
    "card_id": "50069",
    "name": "せいなるはい",
    "count": 1
  },
  {
    "category": "グッズ",
    "card_id": "45931",
    "name": "夜のタンカ",
    "count": 2
  },
  {
    "category": "グッズ",
    "card_id": "45640",
    "name": "アンフェアスタンプ(ACE SPEC)",
    "count": 1
  },
  {
    "category": "ポケモンのどうぐ",
    "card_id": "47618",
    "name": "ふうせん",
    "count": 1
  },
  {
    "category": "ポケモンのどうぐ",
    "card_id": "47704",
    "name": "ブレイブバングル",
    "count": 2
  },
  {
    "category": "サポート",
    "card_id": "47795",
    "name": "リーリエの決心",
    "count": 4
  },
  {
    "category": "サポート",
    "card_id": "43832",
    "name": "ジャッジマン",
    "count": 1
  },
  {
    "category": "サポート",
    "card_id": "44517",
    "name": "ボスの指令",
    "count": 2
  },
  {
    "category": "サポート",
    "card_id": "45637",
    "name": "スイレンのお世話",
    "count": 1
  },
  {
    "category": "サポート",
    "card_id": "45787",
    "name": "スグリ",
    "count": 1
  },
  {
    "category": "サポート",
    "card_id": "46599",
    "name": "からておうの稽古",
    "count": 1
  },
  {
    "category": "スタジアム",
    "card_id": "45790",
    "name": "お祭り会場",
    "count": 4
  },
  {
    "category": "スタジアム",
    "card_id": "47857",
    "name": "活力の森",
    "count": 1
  },
  {
    "category": "エネルギー",
    "card_id": "42779",
    "name": "基本草エネルギー",
    "count": 5
  }
]