[
  {
    "category": "ポケモン",
    "card_id": "46785",
    "name": "タケルライコex",
    "count": 4
  },
  {
    "category": "ポケモン",
    "card_id": "46681",
    "name": "オーガポン みどりのめんex",
    "count": 4
  },
  {
    "category": "ポケモン",
    "card_id": "46409",
    "name": "コライドン",
    "count": 1
  },
  {
    "category": "グッズ",
    "card_id": "49600",
    "name": "ハイパーボール",
    "count": 4
  },
  {
    "category": "グッズ",
    "card_id": "48674",
    "name": "テラスタルオーブ",
    "count": 3
  },
  {
    "category": "グッズ",
    "card_id": "47617",
    "name": "ポケギア3.0",
    "count": 4
  },
  {
    "category": "グッズ",
    "card_id": "49603",
    "name": "ポケモンキャッチャー",
    "count": 4
  },
  {
    "category": "グッズ",
    "card_id": "49352",
    "name": "エネルギー回収",
    "count": 3
  },
  {
    "category": "グッズ",
    "card_id": "49383",
    "name": "むしとりセット",
    "count": 4
  },
  {
    "category": "グッズ",
    "card_id": "49349",
    "name": "アンフェアスタンプ(ACE SPEC)",
    "count": 1
  },
  {
    "category": "サポート",
    "card_id": "49609",
    "name": "リーリエの決心",
    "count": 4
  },
  {
    "category": "サポート",
    "card_id": "49412",
    "name": "アカマツ",
    "count": 4
  },
  {
    "category": "エネルギー",
    "card_id": "47903",
    "name": "基本草エネルギー",
    "count": 12
  },
  {
    "category": "エネルギー",
    "card_id": "47906",
    "name": "基本雷エネルギー",
    "count": 4
  },
  {
    "category": "エネルギー",
    "card_id": "47908",
    "name": "基本闘エネルギー",
    "count": 4
  }
]