[
  {
    "category": "ポケモン",
    "card_id": "45770",
    "name": "ドラメシヤ",
    "count": 4
  },
  {
    "category": "ポケモン",
    "card_id": "45771",
    "name": "ドロンチ",
    "count": 4
  },
  {
    "category": "ポケモン",
    "card_id": "46781",
    "name": "ドラパルトex",
    "count": 2
  },
  {
    "category": "ポケモン",
    "card_id": "47411",
    "name": "アチャモ",
    "count": 2
  },
  {
    "category": "ポケモン",
    "card_id": "47412",
    "name": "ワカシャモ",
    "count": 1
  },
  {
    "category": "ポケモン",
    "card_id": "46470",
    "name": "バシャーモex",
    "count": 2
  },
  {
    "category": "ポケモン",
    "card_id": "48582",
    "name": "リーリエのピッピex",
    "count": 1
  },
  {
    "category": "ポケモン",
    "card_id": "49694",
    "name": "ニャースex",
    "count": 1
  },
  {
    "category": "ポケモン",
    "card_id": "48249",
    "name": "マシマシラ",
    "count": 2
  },
  {
    "category": "ポケモン",
    "card_id": "47301",
    "name": "シェイミ",
    "count": 1
  },
  {
    "category": "ポケモン",
    "card_id": "46662",
    "name": "スボミー",
    "count": 1
  },
  {
    "category": "ポケモン",
    "card_id": "45913",
    "name": "キチキギスex",
    "count": 1
  },
  {
    "category": "ポケモン",
    "card_id": "49862",
    "name": "コダック",
    "count": 1
  },
  {
    "category": "グッズ",
    "card_id": "47172",
    "name": "なかよしポフィン",
    "count": 4
  },
  {
    "category": "グッズ",
    "card_id": "49703",
    "name": "ポケパッド",
    "count": 3
  },
  {
    "category": "グッズ",
    "card_id": "36858",
    "name": "ハイパーボール",
    "count": 3
  },
  {
    "category": "グッズ",
    "card_id": "47265",
    "name": "ふしぎなアメ",
    "count": 3
  },
  {
    "category": "グッズ",
    "card_id": "48681",
    "name": "夜のタンカ",
    "count": 2
  },
  {
    "category": "グッズ",
    "card_id": "50156",
    "name": "スペシャルレッドカード",
    "count": 1
  },
  {
    "category": "サポート",
    "card_id": "49445",
    "name": "リーリエの決心",
    "count": 4
  },
  {
    "category": "サポート",
    "card_id": "48417",
    "name": "ヒカリ",
    "count": 2
  },
  {
    "category": "サポート",
    "card_id": "46101",
    "name": "アカマツ",
    "count": 1
  },
  {
    "category": "サポート",
    "card_id": "45819",
    "name": "ボスの指令",
    "count": 3
  },
  {
    "category": "スタジアム",
    "card_id": "45791",
    "name": "ジャミングタワー",
    "count": 2
  },
  {
    "category": "エネルギー",
    "card_id": "47220",
    "name": "レガシーエネルギー",
    "count": 1
  },
  {
    "category": "エネルギー",
    "card_id": "46117",
    "name": "基本炎エネルギー",
    "count": 3
  },
  {
    "category": "エネルギー",
    "card_id": "46120",
    "name": "基本超エネルギー",
    "count": 3
  },
  {
    "category": "エネルギー",
    "card_id": "46122",
    "name": "基本悪エネルギー",
    "count": 2
  }
]